LICENSE
MANIFEST.in
README.md
setup.py
cvnqplyobj/__init__.py
cvnqplyobj/api_helper.py
cvnqplyobj/configuration.py
cvnqplyobj/cvnqplyobj_client.py
cvnqplyobj/decorators.py
cvnqplyobj.egg-info/PKG-INFO
cvnqplyobj.egg-info/SOURCES.txt
cvnqplyobj.egg-info/dependency_links.txt
cvnqplyobj.egg-info/requires.txt
cvnqplyobj.egg-info/top_level.txt
cvnqplyobj/controllers/__init__.py
cvnqplyobj/controllers/api_controller.py
cvnqplyobj/controllers/base_controller.py
cvnqplyobj/exceptions/__init__.py
cvnqplyobj/exceptions/api_exception.py
cvnqplyobj/http/__init__.py
cvnqplyobj/http/http_call_back.py
cvnqplyobj/http/http_client.py
cvnqplyobj/http/http_context.py
cvnqplyobj/http/http_method_enum.py
cvnqplyobj/http/http_request.py
cvnqplyobj/http/http_response.py
cvnqplyobj/http/requests_client.py
cvnqplyobj/http/auth/__init__.py
cvnqplyobj/http/auth/basic_auth.py
cvnqplyobj/models/__init__.py
cvnqplyobj/models/suite_code_enum.py
tests/__init__.py
tests/http_response_catcher.py
tests/test_helper.py
tests/controllers/__init__.py
tests/controllers/controller_test_base.py
tests/controllers/test_api_controller.py